talkgenerator/__init__.py
talkgenerator/generator.py
talkgenerator/run.py
talkgenerator/runtime_checker.py
talkgenerator/settings.py
talkgenerator/data/images/black-transparent.png
talkgenerator/data/images/error_placeholder.png
talkgenerator/data/powerpoint/template.pptx
talkgenerator/data/prohibited_images/denied.jpg
talkgenerator/data/prohibited_images/huge_domains_ad.gif
talkgenerator/data/prohibited_images/imgur_removed.jpg
talkgenerator/data/prohibited_images/imgur_removed_2.jpg
talkgenerator/data/prohibited_images/tinypic_removed.png
talkgenerator/data/prohibited_images/tinypic_removed2.jpg
talkgenerator/data/text-templates/about_me_facts.json
talkgenerator/data/text-templates/about_me_title.txt
talkgenerator/data/text-templates/anecdote_prompt.txt
talkgenerator/data/text-templates/anecdote_title.txt
talkgenerator/data/text-templates/anticipation_title.txt
talkgenerator/data/text-templates/bold_statements.txt
talkgenerator/data/text-templates/chart_texts.json
talkgenerator/data/text-templates/conclusion_title.txt
talkgenerator/data/text-templates/conclusion_tuple.json
talkgenerator/data/text-templates/deep_abstract.txt
talkgenerator/data/text-templates/default_slide_title.txt
talkgenerator/data/text-templates/double_captions.txt
talkgenerator/data/text-templates/historic_double_captions.txt
talkgenerator/data/text-templates/history.txt
talkgenerator/data/text-templates/history_person.txt
talkgenerator/data/text-templates/inspiration.txt
talkgenerator/data/text-templates/name.json
talkgenerator/data/text-templates/talk_subtitle.json
talkgenerator/data/text-templates/talk_title.json
talkgenerator/data/text-templates/triple_captions.txt
talkgenerator/datastructures/__init__.py
talkgenerator/datastructures/image_data.py
talkgenerator/datastructures/slide_generator_data.py
talkgenerator/schema/__init__.py
talkgenerator/schema/content_generator_structures.py
talkgenerator/schema/content_generators.py
talkgenerator/schema/presentation_schema.py
talkgenerator-2.1.4.dist-info/LICENSE
talkgenerator-2.1.4.dist-info/METADATA
talkgenerator-2.1.4.dist-info/WHEEL
talkgenerator-2.1.4.dist-info/entry_points.txt
talkgenerator-2.1.4.dist-info/top_level.txt
talkgenerator-2.1.4.dist-info/RECORD
